couler/__init__.py
couler/__main__.py
couler/_version.py
couler-0.0.0.dev0.dist-info/LICENSE
couler-0.0.0.dev0.dist-info/METADATA
couler-0.0.0.dev0.dist-info/WHEEL
couler-0.0.0.dev0.dist-info/entry_points.txt
couler-0.0.0.dev0.dist-info/top_level.txt
couler-0.0.0.dev0.dist-info/RECORD
